tnorm/TN_wrapper.py
tnorm/__init__.py
tnorm/app.py
tnorm/norm_ball.py
tnorm/version.py
tnorm/GUI/__init__.py
tnorm/GUI/application.py
tnorm/GUI/browser.py
tnorm/GUI/canvas_image.py
tnorm/GUI/console.py
tnorm/GUI/make_graphic.py
tnorm/GUI/make_table.py
tnorm/GUI/scroll_bars.py
tnorm/GUI/summary_page.py
tnorm/GUI/data/welcome.txt
tnorm/GUI/images/icon/icon.png
tnorm/GUI/images/icon/icon_old.gif
tnorm/GUI/images/spinpoly/poly0.gif
tnorm/GUI/images/spinpoly/poly1.gif
tnorm/GUI/images/spinpoly/poly1.png
tnorm/GUI/images/spinpoly/poly2.gif
tnorm/GUI/images/spinpoly/poly2.png
tnorm/GUI/images/spinpoly/poly3.gif
tnorm/GUI/images/spinpoly/poly3.png
tnorm/GUI/images/spinpoly/poly4.gif
tnorm/GUI/images/spinpoly/poly4.png
tnorm/GUI/images/spinpoly/poly5.gif
tnorm/GUI/images/spinpoly/poly5.png
tnorm/GUI/images/spinpoly/poly6.gif
tnorm/GUI/images/spinpoly/poly6.png
tnorm/GUI/images/spinpoly/poly7.gif
tnorm/GUI/images/spinpoly/poly7.png
tnorm/GUI/images/spinpoly/poly8.gif
tnorm/GUI/images/spinpoly/poly8.png
tnorm/GUI/images/spinpoly/poly9.png
tnorm/GUI/images/spinpoly/poly_gif.gif
tnorm/extras/__init__.py
tnorm/extras/extras.py
tnorm/kernel/__init__.py
tnorm/kernel/abstract_nbhd.py
tnorm/kernel/boundary.py
tnorm/kernel/connected.py
tnorm/kernel/embedded.py
tnorm/kernel/euler.py
tnorm/kernel/homology.py
tnorm/kernel/matrices.py
tnorm/kernel/orientable.py
tnorm/kernel/peripheral.py
tnorm/kernel/simplicial.py
tnorm/test/__init__.py
tnorm/test/test.py
tnorm/utilities/__init__.py
tnorm/utilities/cached_prop.py
tnorm/utilities/file_IO.py
tnorm/utilities/hasse.py
tnorm/utilities/regina_helpers.py
tnorm/utilities/sage_types.py
tnorm/utilities/temp_dir.py
tnorm/utilities/x3d_to_html.py
tnorm/utilities/data/x3d_templates/axes.html
tnorm/utilities/data/x3dom/x3dom.css
tnorm/utilities/data/x3dom/x3dom.js
tnorm-1.0.5.dist-info/LICENSE
tnorm-1.0.5.dist-info/METADATA
tnorm-1.0.5.dist-info/WHEEL
tnorm-1.0.5.dist-info/top_level.txt
tnorm-1.0.5.dist-info/RECORD
