Metadata-Version: 2.1
Name: tnorm
Version: 1.0.5
Home-page: https://github.com/wtworden/TNorm
Author: William Worden
Author-email: wtworden@gmail.com
Classifier: Programming Language :: Python :: 3
Classifier: License :: OSI Approved :: MIT License
Classifier: Operating System :: OS Independent
License-File: LICENSE
Requires-Dist: networkx (>=2.4)
Requires-Dist: snappy (>=3.0)
Requires-Dist: regina (<7.0,>=6.1.0.dev0)
